LICENSE
MANIFEST.in
README.md
setup.py
evmTools_py/__init__.py
evmTools_py/__version__.py
evmTools_py/core.py
evmTools_py.egg-info/PKG-INFO
evmTools_py.egg-info/SOURCES.txt
evmTools_py.egg-info/dependency_links.txt
evmTools_py.egg-info/requires.txt
evmTools_py.egg-info/top_level.txt