Metadata-Version: 2.1
Name: evmTools_py
Version: 0.1.0
Summary: evmtools is a toolkit for developing and testing evm.
Home-page: https://github.com/chenyuan07gis/evmTools
Author: Awesome Soul
Author-email: chenyuan07gis@gmail.com
License: MIT
Classifier: License :: OSI Approved :: MIT License
Classifier: Programming Language :: Python
Classifier: Programming Language :: Python :: 3
Classifier: Programming Language :: Python :: 3.6
Classifier: Programming Language :: Python :: Implementation :: CPython
Classifier: Programming Language :: Python :: Implementation :: PyPy
Requires-Python: >=3.10.0
License-File: LICENSE
Requires-Dist: aiohttp>=3.7.4.post0
Requires-Dist: eth-abi>=4.0.0
Requires-Dist: eth-account>=0.8.0
Requires-Dist: eth-hash[pycryptodome]>=0.5.1
Requires-Dist: eth-typing>=3.0.0
Requires-Dist: eth-utils>=2.1.0
Requires-Dist: hexbytes<0.4.0,>=0.1.0
Requires-Dist: jsonschema>=4.0.0
Requires-Dist: protobuf>=4.21.6
Requires-Dist: pydantic>=2.4.0
Requires-Dist: pywin32>=223; platform_system == "Windows"
Requires-Dist: requests>=2.16.0
Requires-Dist: typing-extensions>=4.0.1
Requires-Dist: websockets>=10.0.0
Requires-Dist: pyunormalize>=15.0.0
